{"1 search page": {"Python developer (Machine Learning Engineer)": {"link": "https://spb.hh.ru/vacancy/72074865?from=vacancy_search_list&query=Python%2C+Django%2C+Flask", "salary": "з/п не указана"}, "Middle разработчик Python / Django": {"link": "https://spb.hh.ru/vacancy/72752600?from=vacancy_search_list&query=Python%2C+Django%2C+Flask", "salary": "от 60 000 до 140 000 руб. на руки"}, "Python разработчик": {"link": "https://spb.hh.ru/vacancy/71069892?from=vacancy_search_list&query=Python%2C+Django%2C+Flask", "salary": "от 160 000 до 200 000 руб. на руки"}, "Программист Python": {"link": "https://spb.hh.ru/vacancy/73581049?from=vacancy_search_list&query=Python%2C+Django%2C+Flask", "salary": "з/п не указана"}, "Middle+ Back-end разработчик (Python)": {"link": "https://spb.hh.ru/vacancy/72379546?from=vacancy_search_list&query=Python%2C+Django%2C+Flask", "salary": "до 200 000 руб. на руки"}, "Middle\\Senior Python Developer": {"link": "https://spb.hh.ru/vacancy/73044031?from=vacancy_search_list&query=Python%2C+Django%2C+Flask", "salary": "от 150 000 до 300 000 руб. на руки"}, "Python developer (удалённо)": {"link": "https://spb.hh.ru/vacancy/73578619?from=vacancy_search_list&query=Python%2C+Django%2C+Flask", "salary": "от 100 000 до 150 000 руб. на руки"}, "Разработчик Python (Senior)": {"link": "https://spb.hh.ru/vacancy/73383410?from=vacancy_search_list&query=Python%2C+Django%2C+Flask", "salary": "з/п не указана"}, "Middle BackEnd разработчик (Python)": {"link": "https://spb.hh.ru/vacancy/72674834?from=vacancy_search_list&query=Python%2C+Django%2C+Flask", "salary": "з/п не указана"}, "Middle+ Backend Python/Django specialist (Сербия)": {"link": "https://spb.hh.ru/vacancy/73532164?from=vacancy_search_list&query=Python%2C+Django%2C+Flask", "salary": "з/п не указана"}, "Python Developer": {"link": "https://spb.hh.ru/vacancy/72488206?from=vacancy_search_list&query=Python%2C+Django%2C+Flask", "salary": "от 4 500 до 5 500 EUR на руки"}, "Python Developer / Telegram Bot Developer / Data Engineer": {"link": "https://spb.hh.ru/vacancy/73500401?from=vacancy_search_list&query=Python%2C+Django%2C+Flask", "salary": "з/п не указана"}, "Python Developer (Backend)": {"link": "https://spb.hh.ru/vacancy/71158485?from=vacancy_search_list&query=Python%2C+Django%2C+Flask", "salary": "з/п не указана"}, "Разработчик Python (Middle)": {"link": "https://spb.hh.ru/vacancy/73523736?from=vacancy_search_list&query=Python%2C+Django%2C+Flask", "salary": "з/п не указана"}, "Python-разработчик (Middle)": {"link": "https://spb.hh.ru/vacancy/73587547?from=vacancy_search_list&query=Python%2C+Django%2C+Flask", "salary": "до 250 000 руб. на руки"}, "Преподаватель Python": {"link": "https://spb.hh.ru/vacancy/73388220?from=vacancy_search_list&query=Python%2C+Django%2C+Flask", "salary": "от 150 000 до 250 000 руб. до вычета налогов"}}, "2 search page": {"Ведущий разработчик Python": {"link": "https://spb.hh.ru/vacancy/73306348?from=vacancy_search_list&query=Python%2C+Django%2C+Flask", "salary": "з/п не указана"}, "Backend developer Python (middle/senior)": {"link": "https://spb.hh.ru/vacancy/71862882?from=vacancy_search_list&query=Python%2C+Django%2C+Flask", "salary": "з/п не указана"}, "Автор курсов по python-разработке в Практикум": {"link": "https://spb.hh.ru/vacancy/73337881?from=vacancy_search_list&query=Python%2C+Django%2C+Flask", "salary": "з/п не указана"}, "Backend Python разработчик (middle+)": {"link": "https://spb.hh.ru/vacancy/72123466?from=vacancy_search_list&query=Python%2C+Django%2C+Flask", "salary": "з/п не указана"}, "Senior бэкенд разработки / Senior backend developer": {"link": "https://spb.hh.ru/vacancy/71023775?from=vacancy_search_list&query=Python%2C+Django%2C+Flask", "salary": "от 350 000 до 350 000 руб. до вычета налогов"}, "Middle/Senior Python developer": {"link": "https://spb.hh.ru/vacancy/40379537?from=vacancy_search_list&query=Python%2C+Django%2C+Flask", "salary": "з/п не указана"}, "Backend разработчик (Python)": {"link": "https://spb.hh.ru/vacancy/71210358?from=vacancy_search_list&query=Python%2C+Django%2C+Flask", "salary": "з/п не указана"}, "Python-developer (Кипр)": {"link": "https://spb.hh.ru/vacancy/72700970?from=vacancy_search_list&query=Python%2C+Django%2C+Flask", "salary": "з/п не указана"}, "Middle Python разработчик": {"link": "https://spb.hh.ru/vacancy/72940395?from=vacancy_search_list&query=Python%2C+Django%2C+Flask", "salary": "з/п не указана"}, "Старший Python + Go разработчик": {"link": "https://spb.hh.ru/vacancy/72195024?from=vacancy_search_list&query=Python%2C+Django%2C+Flask", "salary": "з/п не указана"}, "Python разработчик": {"link": "https://spb.hh.ru/vacancy/72435120?from=vacancy_search_list&query=Python%2C+Django%2C+Flask", "salary": "от 200 000 руб. до вычета налогов"}, "Python Developer (группа автоматизации)": {"link": "https://spb.hh.ru/vacancy/72416568?from=vacancy_search_list&query=Python%2C+Django%2C+Flask", "salary": "з/п не указана"}, "Инженер-программист (отдел новой техники и программирования)": {"link": "https://spb.hh.ru/vacancy/72561693?from=vacancy_search_list&query=Python%2C+Django%2C+Flask", "salary": "з/п не указана"}, "Middle/Middle+ Python разработчик (удаленно)": {"link": "https://spb.hh.ru/vacancy/72938368?from=vacancy_search_list&query=Python%2C+Django%2C+Flask", "salary": "от 120 000 до 170 000 руб. до вычета налогов"}, "Backend разработчик Python midlle": {"link": "https://spb.hh.ru/vacancy/44070869?from=vacancy_search_list&query=Python%2C+Django%2C+Flask", "salary": "з/п не указана"}, "Разработчик EDWH (Python/SQL)": {"link": "https://spb.hh.ru/vacancy/55544528?from=vacancy_search_list&query=Python%2C+Django%2C+Flask", "salary": "з/п не указана"}, "Machine Learning Engineer": {"link": "https://spb.hh.ru/vacancy/71140682?from=vacancy_search_list&query=Python%2C+Django%2C+Flask", "salary": "з/п не указана"}}, "3 search page": {"Senior Python-разработчик": {"link": "https://spb.hh.ru/vacancy/67727675?from=vacancy_search_list&query=Python%2C+Django%2C+Flask", "salary": "з/п не указана"}, "Senior Python разработчик": {"link": "https://spb.hh.ru/vacancy/72351826?from=vacancy_search_list&query=Python%2C+Django%2C+Flask", "salary": "з/п не указана"}, "Python Developer с опытом разработки MRP систем (supply chain, логистика)": {"link": "https://spb.hh.ru/vacancy/72405738?from=vacancy_search_list&query=Python%2C+Django%2C+Flask", "salary": "з/п не указана"}, "Full Stack Software Engineer": {"link": "https://spb.hh.ru/vacancy/71928504?from=vacancy_search_list&query=Python%2C+Django%2C+Flask", "salary": "з/п не указана"}, "Data Scientist (Middle)": {"link": "https://spb.hh.ru/vacancy/72821966?from=vacancy_search_list&query=Python%2C+Django%2C+Flask", "salary": "з/п не указана"}, "Backend developer Python": {"link": "https://spb.hh.ru/vacancy/72696136?from=vacancy_search_list&query=Python%2C+Django%2C+Flask", "salary": "от 3 500 до 5 000 USD на руки"}, "Python Backend Developer": {"link": "https://spb.hh.ru/vacancy/73210720?from=vacancy_search_list&query=Python%2C+Django%2C+Flask", "salary": "от 30 000 до 100 000 руб. на руки"}, "Junior Python разработчик": {"link": "https://spb.hh.ru/vacancy/72554981?from=vacancy_search_list&query=Python%2C+Django%2C+Flask", "salary": "от 60 000 руб. на руки"}, "Data Scientist (Junior)": {"link": "https://spb.hh.ru/vacancy/72820761?from=vacancy_search_list&query=Python%2C+Django%2C+Flask", "salary": "з/п не указана"}, "Системный администратор Linux / DevOps инженер": {"link": "https://spb.hh.ru/vacancy/72408665?from=vacancy_search_list&query=Python%2C+Django%2C+Flask", "salary": "от 100 000 до 200 000 руб. на руки"}, "ГИС инженер": {"link": "https://spb.hh.ru/vacancy/73378685?from=vacancy_search_list&query=Python%2C+Django%2C+Flask", "salary": "з/п не указана"}, "Golang developer": {"link": "https://spb.hh.ru/vacancy/67301394?from=vacancy_search_list&query=Python%2C+Django%2C+Flask", "salary": "з/п не указана"}, "Программист PHP": {"link": "https://spb.hh.ru/vacancy/72359981?from=vacancy_search_list&query=Python%2C+Django%2C+Flask", "salary": "от 70 000 руб. до вычета налогов"}, "Разработчик веб-приложений": {"link": "https://spb.hh.ru/vacancy/73475843?from=vacancy_search_list&query=Python%2C+Django%2C+Flask", "salary": "от 100 000 руб. до вычета налогов"}, "ML Engineer / Machine Learning Operations": {"link": "https://spb.hh.ru/vacancy/73470364?from=vacancy_search_list&query=Python%2C+Django%2C+Flask", "salary": "з/п не указана"}, "Middle Manual QA Engineer": {"link": "https://spb.hh.ru/vacancy/73473161?from=vacancy_search_list&query=Python%2C+Django%2C+Flask", "salary": "от 80 000 до 120 000 руб. на руки"}, "Data Engineer": {"link": "https://spb.hh.ru/vacancy/72312345?from=vacancy_search_list&query=Python%2C+Django%2C+Flask", "salary": "от 200 000 руб. до вычета налогов"}, "Web разработчик (FullStack)": {"link": "https://spb.hh.ru/vacancy/73330839?from=vacancy_search_list&query=Python%2C+Django%2C+Flask", "salary": "от 150 000 до 200 000 руб. на руки"}, "DevOps команды препродуктизации и спецпроектов в сфере ML": {"link": "https://spb.hh.ru/vacancy/71635261?from=vacancy_search_list&query=Python%2C+Django%2C+Flask", "salary": "от 250 000 руб. до вычета налогов"}, "DevOps Engineer": {"link": "https://spb.hh.ru/vacancy/72871624?from=vacancy_search_list&query=Python%2C+Django%2C+Flask", "salary": "з/п не указана"}}}